kinqimen/__init__.py
kinqimen/config.py
kinqimen/kinqimen.py
kinqimen-0.0.6.6.dist-info/METADATA
kinqimen-0.0.6.6.dist-info/WHEEL
kinqimen-0.0.6.6.dist-info/top_level.txt
kinqimen-0.0.6.6.dist-info/RECORD
