Metadata-Version: 2.1
Name: kinqimen
Version: 0.0.6.6
Summary: Qimendunjia (奇門遁甲) is one of the three greatest Chinese Divination systems ever.
Home-page: https://github.com/kentang2017/kinqimen
Author: Ken Tang
Author-email: kinyeah@gmail.com
Classifier: Programming Language :: Python :: 3
Classifier: License :: OSI Approved :: MIT License
Classifier: Operating System :: OS Independent
Requires-Dist: sxtwl ==2.0.6
Requires-Dist: ephem ==4.1.3
